<?xml version="1.0" encoding="UTF-8"?>
<MetaDataObject xmlns="http://v8.1c.ru/8.3/MDClasses" xmlns:app="http://v8.1c.ru/8.2/managed-application/core" xmlns:cfg="http://v8.1c.ru/8.1/data/enterprise/current-config" xmlns:cmi="http://v8.1c.ru/8.2/managed-application/cmi" xmlns:ent="http://v8.1c.ru/8.1/data/enterprise" xmlns:lf="http://v8.1c.ru/8.2/managed-application/logform" xmlns:style="http://v8.1c.ru/8.1/data/ui/style" xmlns:sys="http://v8.1c.ru/8.1/data/ui/fonts/system" xmlns:v8="http://v8.1c.ru/8.1/data/core" xmlns:v8ui="http://v8.1c.ru/8.1/data/ui" xmlns:web="http://v8.1c.ru/8.1/data/ui/colors/web" xmlns:win="http://v8.1c.ru/8.1/data/ui/colors/windows" xmlns:xen="http://v8.1c.ru/8.3/xcf/enums" xmlns:xpr="http://v8.1c.ru/8.3/xcf/predef" xmlns:xr="http://v8.1c.ru/8.3/xcf/readable" xmlns:xs="http://www.w3.org/2001/XMLSchema" xmlns:xsi="http://www.w3.org/2001/XMLSchema-instance" version="2.4">
	<DocumentJournal uuid="6054910e-b72e-4b3c-a9ed-d6da79de79ad">
		<InternalInfo>
			<xr:GeneratedType name="DocumentJournalSelection.ДокументыКонтрагентаБух" category="Selection">
				<xr:TypeId>c8485479-38db-40d8-9510-727bb181a4e3</xr:TypeId>
				<xr:ValueId>37c428a6-3265-44f1-bd55-3e714e224ad5</xr:ValueId>
			</xr:GeneratedType>
			<xr:GeneratedType name="DocumentJournalList.ДокументыКонтрагентаБух" category="List">
				<xr:TypeId>861ad8be-e475-4f4c-a322-b9875d37a438</xr:TypeId>
				<xr:ValueId>4c1750d7-ca5c-4aec-ad17-e39bb6ff6f45</xr:ValueId>
			</xr:GeneratedType>
			<xr:GeneratedType name="DocumentJournalManager.ДокументыКонтрагентаБух" category="Manager">
				<xr:TypeId>595be7ca-da1f-4ad1-a317-66cd6bfd72e0</xr:TypeId>
				<xr:ValueId>4dd0e211-e07d-4638-9619-48e050b06096</xr:ValueId>
			</xr:GeneratedType>
		</InternalInfo>
		<Properties>
			<Name>ДокументыКонтрагентаБух</Name>
			<Synonym>
				<v8:item>
					<v8:lang>ru</v8:lang>
					<v8:content>Документы контрагента (бух.)</v8:content>
				</v8:item>
			</Synonym>
			<Comment/>
			<DefaultForm>DocumentJournal.ДокументыКонтрагентаБух.Form.ФормаСписка</DefaultForm>
			<AuxiliaryForm/>
			<UseStandardCommands>true</UseStandardCommands>
			<RegisteredDocuments>
				<xr:Item xsi:type="xr:MDObjectRef">Document.АктСверкиВзаиморасчетов</xr:Item>
				<xr:Item xsi:type="xr:MDObjectRef">Document.АктПеревозчика</xr:Item>
				<xr:Item xsi:type="xr:MDObjectRef">Document.АвансовыйОтчет</xr:Item>
				<xr:Item xsi:type="xr:MDObjectRef">Document.ВозвратТоваровПоставщику</xr:Item>
				<xr:Item xsi:type="xr:MDObjectRef">Document.ЗаключениеДоговораАренды</xr:Item>
				<xr:Item xsi:type="xr:MDObjectRef">Document.ЗакрытиеУслуг</xr:Item>
				<xr:Item xsi:type="xr:MDObjectRef">Document.ЗачетОплатыАренды</xr:Item>
				<xr:Item xsi:type="xr:MDObjectRef">Document.ЗаявкаНаРасходованиеСредств</xr:Item>
				<xr:Item xsi:type="xr:MDObjectRef">Document.НачислениеАренднойПлатыАрендаторам</xr:Item>
				<xr:Item xsi:type="xr:MDObjectRef">Document.НачислениеАренднойПлатыОтАрендодателей</xr:Item>
				<xr:Item xsi:type="xr:MDObjectRef">Document.ОбщиеТранспортныеРасходы</xr:Item>
				<xr:Item xsi:type="xr:MDObjectRef">Document.ПоступлениеВБанк</xr:Item>
				<xr:Item xsi:type="xr:MDObjectRef">Document.ПоступлениеВКассу</xr:Item>
				<xr:Item xsi:type="xr:MDObjectRef">Document.ПоступлениеТоваровУслуг</xr:Item>
				<xr:Item xsi:type="xr:MDObjectRef">Document.РасторжениеДоговораАренды</xr:Item>
				<xr:Item xsi:type="xr:MDObjectRef">Document.РасходИзБанка</xr:Item>
				<xr:Item xsi:type="xr:MDObjectRef">Document.РасходИзКассы</xr:Item>
				<xr:Item xsi:type="xr:MDObjectRef">Document.РеализацияТоваровУслуг</xr:Item>
				<xr:Item xsi:type="xr:MDObjectRef">Document.ТранспортныеРасходы</xr:Item>
				<xr:Item xsi:type="xr:MDObjectRef">Document.ШтрафыПриДоставкеНаТорговыеТочки</xr:Item>
				<xr:Item xsi:type="xr:MDObjectRef">Document.ДополнительноеСоглашение</xr:Item>
				<xr:Item xsi:type="xr:MDObjectRef">Document.ДоставкаНаТТ</xr:Item>
				<xr:Item xsi:type="xr:MDObjectRef">Document.ПереносЗадолженностиМеждуКонтрагентами</xr:Item>
			</RegisteredDocuments>
			<IncludeHelpInContents>false</IncludeHelpInContents>
			<ListPresentation/>
			<ExtendedListPresentation/>
			<Explanation/>
		</Properties>
		<ChildObjects>
			<Column uuid="f6120f6c-f22d-456a-a655-ec9a585c8232">
				<Properties>
					<Name>ВидОперации</Name>
					<Synonym>
						<v8:item>
							<v8:lang>ru</v8:lang>
							<v8:content>Вид операции</v8:content>
						</v8:item>
					</Synonym>
					<Comment/>
					<Indexing>DontIndex</Indexing>
					<References>
						<xr:Item xsi:type="xr:MDObjectRef">Document.АвансовыйОтчет.Attribute.ВидОперации</xr:Item>
						<xr:Item xsi:type="xr:MDObjectRef">Document.АктПеревозчика.Attribute.ВидОперации</xr:Item>
						<xr:Item xsi:type="xr:MDObjectRef">Document.ВозвратТоваровПоставщику.Attribute.ВидОперации</xr:Item>
						<xr:Item xsi:type="xr:MDObjectRef">Document.ЗаключениеДоговораАренды.Attribute.ВидОперации</xr:Item>
						<xr:Item xsi:type="xr:MDObjectRef">Document.ПоступлениеВБанк.Attribute.ВидОперации</xr:Item>
						<xr:Item xsi:type="xr:MDObjectRef">Document.ПоступлениеВКассу.Attribute.ВидОперации</xr:Item>
						<xr:Item xsi:type="xr:MDObjectRef">Document.ПоступлениеТоваровУслуг.Attribute.ВидОперации</xr:Item>
						<xr:Item xsi:type="xr:MDObjectRef">Document.РасходИзБанка.Attribute.ВидОперации</xr:Item>
						<xr:Item xsi:type="xr:MDObjectRef">Document.РасходИзКассы.Attribute.ВидОперации</xr:Item>
					</References>
				</Properties>
			</Column>
			<Column uuid="4b0e2811-34b7-4098-b2de-62d94734c5a1">
				<Properties>
					<Name>Организация</Name>
					<Synonym>
						<v8:item>
							<v8:lang>ru</v8:lang>
							<v8:content>Организация</v8:content>
						</v8:item>
					</Synonym>
					<Comment/>
					<Indexing>DontIndex</Indexing>
					<References>
						<xr:Item xsi:type="xr:MDObjectRef">Document.АвансовыйОтчет.Attribute.Организация</xr:Item>
						<xr:Item xsi:type="xr:MDObjectRef">Document.АктПеревозчика.Attribute.Организация</xr:Item>
						<xr:Item xsi:type="xr:MDObjectRef">Document.АктСверкиВзаиморасчетов.Attribute.Организация</xr:Item>
						<xr:Item xsi:type="xr:MDObjectRef">Document.ВозвратТоваровПоставщику.Attribute.Организация</xr:Item>
						<xr:Item xsi:type="xr:MDObjectRef">Document.ДополнительноеСоглашение.Attribute.Организация</xr:Item>
						<xr:Item xsi:type="xr:MDObjectRef">Document.ДоставкаНаТТ.Attribute.Организация</xr:Item>
						<xr:Item xsi:type="xr:MDObjectRef">Document.ЗаключениеДоговораАренды.Attribute.Организация</xr:Item>
						<xr:Item xsi:type="xr:MDObjectRef">Document.ЗакрытиеУслуг.Attribute.Организация</xr:Item>
						<xr:Item xsi:type="xr:MDObjectRef">Document.ЗачетОплатыАренды.Attribute.Организация</xr:Item>
						<xr:Item xsi:type="xr:MDObjectRef">Document.ЗаявкаНаРасходованиеСредств.Attribute.Организация</xr:Item>
						<xr:Item xsi:type="xr:MDObjectRef">Document.НачислениеАренднойПлатыАрендаторам.Attribute.Организация</xr:Item>
						<xr:Item xsi:type="xr:MDObjectRef">Document.ОбщиеТранспортныеРасходы.Attribute.Организация</xr:Item>
						<xr:Item xsi:type="xr:MDObjectRef">Document.ПереносЗадолженностиМеждуКонтрагентами.Attribute.Организация</xr:Item>
						<xr:Item xsi:type="xr:MDObjectRef">Document.ПоступлениеВБанк.Attribute.Организация</xr:Item>
						<xr:Item xsi:type="xr:MDObjectRef">Document.ПоступлениеВКассу.Attribute.Организация</xr:Item>
						<xr:Item xsi:type="xr:MDObjectRef">Document.ПоступлениеТоваровУслуг.Attribute.Организация</xr:Item>
						<xr:Item xsi:type="xr:MDObjectRef">Document.РасторжениеДоговораАренды.Attribute.Организация</xr:Item>
						<xr:Item xsi:type="xr:MDObjectRef">Document.РасходИзБанка.Attribute.Организация</xr:Item>
						<xr:Item xsi:type="xr:MDObjectRef">Document.РасходИзКассы.Attribute.Организация</xr:Item>
						<xr:Item xsi:type="xr:MDObjectRef">Document.РеализацияТоваровУслуг.Attribute.Организация</xr:Item>
						<xr:Item xsi:type="xr:MDObjectRef">Document.ТранспортныеРасходы.Attribute.Организация</xr:Item>
						<xr:Item xsi:type="xr:MDObjectRef">Document.ШтрафыПриДоставкеНаТорговыеТочки.Attribute.Организация</xr:Item>
					</References>
				</Properties>
			</Column>
			<Column uuid="dc1f5f58-0b63-4d95-9ce2-492249b2b2dd">
				<Properties>
					<Name>Контрагент</Name>
					<Synonym>
						<v8:item>
							<v8:lang>ru</v8:lang>
							<v8:content>Контрагент</v8:content>
						</v8:item>
					</Synonym>
					<Comment/>
					<Indexing>DontIndex</Indexing>
					<References>
						<xr:Item xsi:type="xr:MDObjectRef">Document.АктПеревозчика.Attribute.Перевозчик</xr:Item>
						<xr:Item xsi:type="xr:MDObjectRef">Document.АктСверкиВзаиморасчетов.Attribute.Контрагент</xr:Item>
						<xr:Item xsi:type="xr:MDObjectRef">Document.ВозвратТоваровПоставщику.Attribute.Контрагент</xr:Item>
						<xr:Item xsi:type="xr:MDObjectRef">Document.ДополнительноеСоглашение.Attribute.Контрагент</xr:Item>
						<xr:Item xsi:type="xr:MDObjectRef">Document.ДоставкаНаТТ.Attribute.Контрагент</xr:Item>
						<xr:Item xsi:type="xr:MDObjectRef">Document.ЗаключениеДоговораАренды.Attribute.Контрагент</xr:Item>
						<xr:Item xsi:type="xr:MDObjectRef">Document.ЗакрытиеУслуг.Attribute.Контрагент</xr:Item>
						<xr:Item xsi:type="xr:MDObjectRef">Document.ЗачетОплатыАренды.Attribute.Контрагент</xr:Item>
						<xr:Item xsi:type="xr:MDObjectRef">Document.ЗаявкаНаРасходованиеСредств.Attribute.Контрагент</xr:Item>
						<xr:Item xsi:type="xr:MDObjectRef">Document.ОбщиеТранспортныеРасходы.Attribute.Перевозчик</xr:Item>
						<xr:Item xsi:type="xr:MDObjectRef">Document.ПоступлениеВБанк.Attribute.Контрагент</xr:Item>
						<xr:Item xsi:type="xr:MDObjectRef">Document.ПоступлениеВКассу.Attribute.Контрагент</xr:Item>
						<xr:Item xsi:type="xr:MDObjectRef">Document.ПоступлениеТоваровУслуг.Attribute.Контрагент</xr:Item>
						<xr:Item xsi:type="xr:MDObjectRef">Document.РасторжениеДоговораАренды.Attribute.Контрагент</xr:Item>
						<xr:Item xsi:type="xr:MDObjectRef">Document.РасходИзБанка.Attribute.Контрагент</xr:Item>
						<xr:Item xsi:type="xr:MDObjectRef">Document.РасходИзКассы.Attribute.Контрагент</xr:Item>
						<xr:Item xsi:type="xr:MDObjectRef">Document.РеализацияТоваровУслуг.Attribute.Контрагент</xr:Item>
						<xr:Item xsi:type="xr:MDObjectRef">Document.ТранспортныеРасходы.Attribute.Перевозчик</xr:Item>
					</References>
				</Properties>
			</Column>
			<Column uuid="4760771b-263c-465c-bb27-744c3f3a638a">
				<Properties>
					<Name>Сумма</Name>
					<Synonym>
						<v8:item>
							<v8:lang>ru</v8:lang>
							<v8:content>Сумма</v8:content>
						</v8:item>
					</Synonym>
					<Comment/>
					<Indexing>DontIndex</Indexing>
					<References>
						<xr:Item xsi:type="xr:MDObjectRef">Document.АвансовыйОтчет.Attribute.СуммаДокумента</xr:Item>
						<xr:Item xsi:type="xr:MDObjectRef">Document.ВозвратТоваровПоставщику.Attribute.СуммаДокумента</xr:Item>
						<xr:Item xsi:type="xr:MDObjectRef">Document.ДоставкаНаТТ.Attribute.СуммаДокумента</xr:Item>
						<xr:Item xsi:type="xr:MDObjectRef">Document.ЗаявкаНаРасходованиеСредств.Attribute.СуммаДокумента</xr:Item>
						<xr:Item xsi:type="xr:MDObjectRef">Document.ОбщиеТранспортныеРасходы.Attribute.Сумма</xr:Item>
						<xr:Item xsi:type="xr:MDObjectRef">Document.ПоступлениеВБанк.Attribute.СуммаДокумента</xr:Item>
						<xr:Item xsi:type="xr:MDObjectRef">Document.ПоступлениеВКассу.Attribute.СуммаДокумента</xr:Item>
						<xr:Item xsi:type="xr:MDObjectRef">Document.ПоступлениеТоваровУслуг.Attribute.СуммаДокумента</xr:Item>
						<xr:Item xsi:type="xr:MDObjectRef">Document.РасходИзБанка.Attribute.СуммаДокумента</xr:Item>
						<xr:Item xsi:type="xr:MDObjectRef">Document.РасторжениеДоговораАренды.Attribute.СуммаЗалога</xr:Item>
						<xr:Item xsi:type="xr:MDObjectRef">Document.РасходИзКассы.Attribute.СуммаДокумента</xr:Item>
						<xr:Item xsi:type="xr:MDObjectRef">Document.РеализацияТоваровУслуг.Attribute.СуммаДокумента</xr:Item>
						<xr:Item xsi:type="xr:MDObjectRef">Document.ТранспортныеРасходы.Attribute.Сумма</xr:Item>
					</References>
				</Properties>
			</Column>
			<Column uuid="22b90323-f2eb-480e-a835-85b1ec628622">
				<Properties>
					<Name>Ответственный</Name>
					<Synonym>
						<v8:item>
							<v8:lang>ru</v8:lang>
							<v8:content>Ответственный</v8:content>
						</v8:item>
					</Synonym>
					<Comment/>
					<Indexing>DontIndex</Indexing>
					<References>
						<xr:Item xsi:type="xr:MDObjectRef">Document.АвансовыйОтчет.Attribute.Ответственный</xr:Item>
						<xr:Item xsi:type="xr:MDObjectRef">Document.АктСверкиВзаиморасчетов.Attribute.Ответственный</xr:Item>
						<xr:Item xsi:type="xr:MDObjectRef">Document.ВозвратТоваровПоставщику.Attribute.Ответственный</xr:Item>
						<xr:Item xsi:type="xr:MDObjectRef">Document.ДополнительноеСоглашение.Attribute.Ответственный</xr:Item>
						<xr:Item xsi:type="xr:MDObjectRef">Document.ДоставкаНаТТ.Attribute.Ответственный</xr:Item>
						<xr:Item xsi:type="xr:MDObjectRef">Document.ЗаключениеДоговораАренды.Attribute.Ответственный</xr:Item>
						<xr:Item xsi:type="xr:MDObjectRef">Document.ЗакрытиеУслуг.Attribute.Ответственный</xr:Item>
						<xr:Item xsi:type="xr:MDObjectRef">Document.ЗачетОплатыАренды.Attribute.Ответственный</xr:Item>
						<xr:Item xsi:type="xr:MDObjectRef">Document.НачислениеАренднойПлатыАрендаторам.Attribute.Ответственный</xr:Item>
						<xr:Item xsi:type="xr:MDObjectRef">Document.ЗаявкаНаРасходованиеСредств.Attribute.Ответственный</xr:Item>
						<xr:Item xsi:type="xr:MDObjectRef">Document.НачислениеАренднойПлатыОтАрендодателей.Attribute.Ответственный</xr:Item>
						<xr:Item xsi:type="xr:MDObjectRef">Document.ПереносЗадолженностиМеждуКонтрагентами.Attribute.Ответственный</xr:Item>
						<xr:Item xsi:type="xr:MDObjectRef">Document.ПоступлениеВБанк.Attribute.Ответственный</xr:Item>
						<xr:Item xsi:type="xr:MDObjectRef">Document.ПоступлениеВКассу.Attribute.Ответственный</xr:Item>
						<xr:Item xsi:type="xr:MDObjectRef">Document.ПоступлениеТоваровУслуг.Attribute.Ответственный</xr:Item>
						<xr:Item xsi:type="xr:MDObjectRef">Document.РасторжениеДоговораАренды.Attribute.Ответственный</xr:Item>
						<xr:Item xsi:type="xr:MDObjectRef">Document.РасходИзБанка.Attribute.Ответственный</xr:Item>
						<xr:Item xsi:type="xr:MDObjectRef">Document.РасходИзКассы.Attribute.Ответственный</xr:Item>
						<xr:Item xsi:type="xr:MDObjectRef">Document.РеализацияТоваровУслуг.Attribute.Ответственный</xr:Item>
						<xr:Item xsi:type="xr:MDObjectRef">Document.ОбщиеТранспортныеРасходы.Attribute.Автор</xr:Item>
						<xr:Item xsi:type="xr:MDObjectRef">Document.ТранспортныеРасходы.Attribute.Автор</xr:Item>
						<xr:Item xsi:type="xr:MDObjectRef">Document.ШтрафыПриДоставкеНаТорговыеТочки.Attribute.Автор</xr:Item>
						<xr:Item xsi:type="xr:MDObjectRef">Document.АктПеревозчика.Attribute.Автор</xr:Item>
					</References>
				</Properties>
			</Column>
			<Form>ФормаСписка</Form>
		</ChildObjects>
	</DocumentJournal>
</MetaDataObject>